aucurriculum/__init__.py
aucurriculum/cli/__init__.py
aucurriculum/core/__init__.py
aucurriculum/core/constants/__init__.py
aucurriculum/core/constants/curriculum_constants.py
aucurriculum/core/filters/__init__.py
aucurriculum/core/filters/filters.py
aucurriculum/core/plotting/__init__.py
aucurriculum/core/plotting/plot_curriculum.py
aucurriculum/core/scripts/__init__.py
aucurriculum/core/scripts/cli.py
aucurriculum/core/scripts/cli_wrapper.py
aucurriculum/core/scripts/create_script.py
aucurriculum/core/scripts/curriculum_script.py
aucurriculum/core/scripts/group_script.py
aucurriculum/core/scripts/list_script.py
aucurriculum/core/scripts/postprocess_script.py
aucurriculum/core/scripts/show_script.py
aucurriculum/core/scripts/train_script.py
aucurriculum/core/wrappers/__init__.py
aucurriculum/core/wrappers/main.py
aucurriculum/curricula/__init__.py
aucurriculum/curricula/curriculum_pace_manager.py
aucurriculum/curricula/curriculum_score_manager.py
aucurriculum/curricula/pacing/__init__.py
aucurriculum/curricula/pacing/abstract_pace.py
aucurriculum/curricula/pacing/exponential.py
aucurriculum/curricula/pacing/logarithmic.py
aucurriculum/curricula/pacing/one_step.py
aucurriculum/curricula/pacing/polynomial.py
aucurriculum/curricula/scoring/__init__.py
aucurriculum/curricula/scoring/abstract_score.py
aucurriculum/curricula/scoring/ce_loss.py
aucurriculum/curricula/scoring/cumulative_accuracy.py
aucurriculum/curricula/scoring/cv_loss.py
aucurriculum/curricula/scoring/first_iteration.py
aucurriculum/curricula/scoring/predefined_score.py
aucurriculum/curricula/scoring/prediction_depth.py
aucurriculum/curricula/scoring/random_score.py
aucurriculum/curricula/scoring/transfer_teacher.py
aucurriculum/curricula/scoring/utils.py
aucurriculum/postprocessing/__init__.py
aucurriculum/postprocessing/aggregate.py
aucurriculum/postprocessing/group.py
aucurriculum/postprocessing/summarize_curriculum.py
aucurriculum-configurations/_aucurriculum_score_.yaml
aucurriculum-0.1.1.dist-info/LICENSE
aucurriculum-0.1.1.dist-info/METADATA
aucurriculum-0.1.1.dist-info/WHEEL
aucurriculum-0.1.1.dist-info/entry_points.txt
aucurriculum-0.1.1.dist-info/RECORD
