Metadata-Version: 2.1
Name: aucurriculum
Version: 0.1.1
Summary: A Curriculum Learning Toolkit for Deep Learning Tasks built on top of autrainer.
Home-page: https://github.com/autrainer/aucurriculum
License: MIT
Keywords: curriculum learning,autrainer,computer audition,deep learning,artificial intelligence,pytorch,hydra-core,command-line,yaml
Author: Simon Rampp
Author-email: simon.rampp@tum.de
Requires-Python: >=3.9,<4.0
Classifier: License :: OSI Approved :: MIT License
Classifier: Operating System :: OS Independent
Classifier: Programming Language :: Python :: 3
Classifier: Programming Language :: Python :: 3.9
Classifier: Programming Language :: Python :: 3.10
Classifier: Programming Language :: Python :: 3.11
Classifier: Programming Language :: Python :: 3.12
Classifier: Programming Language :: Python :: 3.13
Requires-Dist: autrainer (==0.4.0)
Project-URL: Documentation, https://autrainer.github.io/aucurriculum/
Project-URL: Repository, https://github.com/autrainer/aucurriculum
